[{"place_id": 64709307, "licence": "Data \u00a9 OpenStreetMap contributors, ODbL 1.0. http://osm.org/copyright", "osm_type": "node", "osm_id": 11083054726, "lat": "47.4007479", "lon": "8.9561410", "class": "place", "type": "locality", "place_rank": 25, "importance": 0.06671311284046692, "addresstype": "locality", "name": "Stadelberg", "display_name": "Stadelberg, Au TG, Fischingen, Bezirk M\u00fcnchwilen, Thurgau, 8376, Switzerland", "boundingbox": ["47.3907479", "47.4107479", "8.9461410", "8.9661410"]}]