[{"place_id": 85206386, "licence": "Data \u00a9 OpenStreetMap contributors, ODbL 1.0. http://osm.org/copyright", "osm_type": "relation", "osm_id": 116660, "lat": "46.0292761", "lon": "1.4188089", "class": "boundary", "type": "administrative", "place_rank": 16, "importance": 0.5121271057478117, "addresstype": "village", "name": "Saint-L\u00e9ger-la-Montagne", "display_name": "Saint-L\u00e9ger-la-Montagne, Limoges, Haute-Vienne, Nouvelle-Aquitaine, Metropolitan France, 87340, France", "boundingbox": ["46.0008384", "46.0613664", "1.3740516", "1.4813286"]}]