[{"place_id": 16261978, "licence": "Data \u00a9 OpenStreetMap contributors, ODbL 1.0. http://osm.org/copyright", "osm_type": "node", "osm_id": 5206871927, "lat": "-34.6097193", "lon": "-58.3741190", "class": "railway", "type": "station", "place_rank": 30, "importance": 0.39597344892030606, "addresstype": "railway", "name": "Bol\u00edvar", "display_name": "Bol\u00edvar, Avenida Presidente Julio A. Roca, Monserrat, Buenos Aires, Comuna 1, Autonomous City of Buenos Aires, C1067AAC, Argentina", "boundingbox": ["-34.6147193", "-34.6047193", "-58.3791190", "-58.3691190"]}]