[{"place_id": 91379345, "licence": "Data \u00a9 OpenStreetMap contributors, ODbL 1.0. http://osm.org/copyright", "osm_type": "relation", "osm_id": 2582302, "lat": "51.0791335", "lon": "1.1794073", "class": "boundary", "type": "administrative", "place_rank": 20, "importance": 0.5402947262214048, "addresstype": "town", "name": "Folkestone", "display_name": "Folkestone, Folkestone and Hythe District, Kent, England, United Kingdom", "boundingbox": ["51.0717272", "51.1051871", "1.1192870", "1.2212358"]}]