[{"place_id": 27627131, "licence": "Data \u00a9 OpenStreetMap contributors, ODbL 1.0. http://osm.org/copyright", "osm_type": "relation", "osm_id": 9687063, "lat": "-7.5692489", "lon": "110.8284480", "class": "boundary", "type": "administrative", "place_rank": 12, "importance": 0.5598229429954946, "addresstype": "city", "name": "Surakarta", "display_name": "Surakarta, Kecamatan Pasar Kliwon, Central Java, Java, Indonesia", "boundingbox": ["-7.5952116", "-7.5232191", "110.7690994", "110.8689442"]}]