[{"place_id": 171186637, "licence": "Data \u00a9 OpenStreetMap contributors, ODbL 1.0. http://osm.org/copyright", "osm_type": "relation", "osm_id": 3300833, "lat": "49.6600228", "lon": "19.5579106", "class": "boundary", "type": "administrative", "place_rank": 16, "importance": 0.39195931779043985, "addresstype": "village", "name": "Zawoja", "display_name": "Zawoja, gmina Zawoja, Sucha County, Lesser Poland Voivodeship, Poland", "boundingbox": ["49.5721470", "49.6987344", "19.4673762", "19.6192452"]}]