[{"place_id": 18735682, "licence": "Data \u00a9 OpenStreetMap contributors, ODbL 1.0. http://osm.org/copyright", "osm_type": "node", "osm_id": 27071462, "lat": "-37.8752637", "lon": "145.1281258", "class": "railway", "type": "station", "place_rank": 30, "importance": 0.3701707379334754, "addresstype": "railway", "name": "Mount Waverley", "display_name": "Mount Waverley, Waverley Rail Trail, Mount Waverley, Melbourne, City of Monash, Victoria, 3149, Australia", "boundingbox": ["-37.8802637", "-37.8702637", "145.1231258", "145.1331258"]}]