[{"place_id": 294427404, "licence": "Data \u00a9 OpenStreetMap contributors, ODbL 1.0. http://osm.org/copyright", "osm_type": "relation", "osm_id": 4596982, "lat": "20.4044622", "lon": "-97.2892457", "class": "boundary", "type": "administrative", "place_rank": 16, "importance": 0.18671666819256882, "addresstype": "city", "name": "Cerro del Carb\u00f3n", "display_name": "Cerro del Carb\u00f3n, Terrenos del Lote 11 \"Cerro del Carb\u00f3n\", Papantla, Veracruz, Mexico", "boundingbox": ["20.4029010", "20.4062471", "-97.2914782", "-97.2844774"]}]