[{"place_id": 80880992, "licence": "Data \u00a9 OpenStreetMap contributors, ODbL 1.0. http://osm.org/copyright", "osm_type": "way", "osm_id": 104573411, "lat": "45.7244237", "lon": "5.0865172", "class": "aeroway", "type": "aerodrome", "place_rank": 30, "importance": 0.5271847881190028, "addresstype": "aeroway", "name": "Lyon-Saint Exup\u00e9ry Airport", "display_name": "Lyon-Saint Exup\u00e9ry Airport, Rue de Bulgarie, Colombier-Saugnieu, Lyon, Rh\u00f4ne, Auvergne-Rh\u00f4ne-Alpes, Metropolitan France, 69124, France", "boundingbox": ["45.6962433", "45.7528130", "5.0755059", "5.0991477"]}]